detadict/__init__.py
detadict/detadict.py
detadict-0.1.0.dist-info/LICENSE
detadict-0.1.0.dist-info/WHEEL
detadict-0.1.0.dist-info/METADATA
detadict-0.1.0.dist-info/RECORD
