Metadata-Version: 2.1
Name: detadict
Version: 0.1.0
Summary: Python dict with Deta backend
Home-page: https://github.com/ilhomidin/detadict
License: MIT
Keywords: deta,dict
Author: ilhomidin
Author-email: itilhomidin@yandex.com
Requires-Python: >=3.7,<4.0
Classifier: Development Status :: 3 - Alpha
Classifier: Intended Audience :: Developers
Classifier: License :: OSI Approved :: MIT License
Classifier: Programming Language :: Python :: 3
Classifier: Programming Language :: Python :: 3.7
Classifier: Programming Language :: Python :: 3.8
Classifier: Programming Language :: Python :: 3.9
Requires-Dist: deta (>=1.0.0,<2.0.0)
Project-URL: Repository, https://github.com/ilhomidin/detadict
